{"cameraMode":{"drawMode":0,"name":"Shaded","section":"Shading Mode"},"sceneLighting":true,"audioPlay":false,"sceneViewState":{"m_AlwaysRefresh":false,"showFog":true,"showSkybox":true,"showFlares":true,"showImageEffects":true,"showParticleSystems":true,"showVisualEffectGraphs":true,"m_FxEnabled":true},"in2DMode":false,"pivot":{"x":-162.34364318847657,"y":-145.2513427734375,"z":-366.257080078125},"rotation":{"x":0.03667597100138664,"y":-0.9625110626220703,"z":0.16548599302768708,"w":0.2121497541666031},"size":222.25999450683595,"orthographic":false}